hoverboard/__init__.py
hoverboard-0.0.1.dist-info/LICENSE.txt
hoverboard-0.0.1.dist-info/METADATA
hoverboard-0.0.1.dist-info/WHEEL
hoverboard-0.0.1.dist-info/top_level.txt
hoverboard-0.0.1.dist-info/RECORD
