Metadata-Version: 2.1
Name: hoverboard
Version: 0.0.1
Author: Yossi Rosilio
Author-email: yossirozolyoo@hotmail.com
License: MIT
Classifier: Programming Language :: Python :: 3
Classifier: Topic :: System :: Hardware
License-File: LICENSE.txt
